kineticpool
