Metadata-Version: 1.1
Name: kineticpool
Version: 0.2.0
Summary: A python connections manager for Kinetic devices
Home-page: https://github.com/Seagate/kinetic-pool-py
Author: Ignacio Corderi
Author-email: UNKNOWN
License: MIT
Keywords: kinetic connection pool storage key/value seagate
Platform: UNKNOWN
Classifier: Development Status :: 4 - Beta
Classifier: Intended Audience :: Developers
Classifier: Intended Audience :: Information Technology
Classifier: License :: OSI Approved :: MIT License
Classifier: Programming Language :: Python :: 2.7
Classifier: Programming Language :: Python :: 2 :: Only
Classifier: Topic :: Software Development :: Libraries :: Python Modules
